ExoPSI/__init__.py
ExoPSI/exopsi.py
ExoPSI/subfunctions.py
ExoPSI-1.0.5.dist-info/LICENSE
ExoPSI-1.0.5.dist-info/METADATA
ExoPSI-1.0.5.dist-info/WHEEL
ExoPSI-1.0.5.dist-info/top_level.txt
ExoPSI-1.0.5.dist-info/RECORD
