Metadata-Version: 2.1
Name: ExoPSI
Version: 1.0.5
Summary: Library to calculate Planet Similarity Indexes
Home-page: https://github.com/ExoPSI/ExoPSI
Author: ['Aditya Rai', 'Vaibhav Garg', 'Divya Srinivasan']
Author-email: rai.aditya01@gmail.com
License: GNU GPL v3.0
Classifier: Intended Audience :: Developers
Classifier: License :: OSI Approved :: GNU General Public License v3 (GPLv3)
Classifier: Programming Language :: Python
Classifier: Programming Language :: Python :: 3
Classifier: Programming Language :: Python :: 3.6
Classifier: Programming Language :: Python :: 3.7
Classifier: Programming Language :: Python :: 3.8
Classifier: Programming Language :: Python :: 3.9
Classifier: Operating System :: OS Independent
License-File: LICENSE
Requires-Dist: numpy
Requires-Dist: matplotlib
Requires-Dist: pandas
